{
    "behavior": "", 
    "checkable": false, 
    "class": "div", 
    "clickable": false, 
    "content-desc": "", 
    "enabled": false, 
    "focusable": false, 
    "focused": false, 
    "hash": "h5kvmnmRp0sszEs99QUfRQ==\n", 
    "height": 32, 
    "hier_level": 0, 
    "human_hash": "div_X1816_Y567_W48_H32", 
    "index": -1, 
    "internal": {
        "elem_dict": {
            "attributes": {
                "style": "display: flex; flex-direction: row-reverse; align-items: center;"
            }, 
            "background-color": "rgba(0, 0, 0, 0)", 
            "class": "div", 
            "color": "rgb(0, 0, 0)", 
            "domLevel": 39, 
            "flags": {
                "checkable": false, 
                "clickable": false, 
                "enabled": false, 
                "focusable": false, 
                "focused": false, 
                "scrollable": false
            }, 
            "font-family": "Inter, OpenSans, Helvetica, Arial, sans-serif", 
            "font-weight": "400", 
            "fontSize": 16, 
            "height": 32, 
            "identifier": "", 
            "is-focused": false, 
            "is-hidden": false, 
            "name": "", 
            "tagName": "div", 
            "text": "", 
            "type": "", 
            "value": "", 
            "width": 48, 
            "x": 1816, 
            "xPercent": 94.58333333333333, 
            "y": 567, 
            "yPercent": 63.99548532731377
        }, 
        "location": {
            "x": 1816, 
            "y": 567
        }, 
        "size": {
            "height": 32, 
            "width": 48
        }, 
        "tag_name": "div", 
        "text": ""
    }, 
    "is_transformed": true, 
    "package": "", 
    "password": false, 
    "resource-id": "", 
    "scrollable": false, 
    "tag_name": "div", 
    "text": "", 
    "transformed": true, 
    "width": 48, 
    "x": 1816, 
    "y": 567
}