{
    "behavior": "", 
    "checkable": false, 
    "class": "div", 
    "clickable": false, 
    "content-desc": "", 
    "enabled": false, 
    "focusable": false, 
    "focused": false, 
    "hash": "wE/rd4upr/Wl5QZTQX1qDw==\n", 
    "height": 287, 
    "hier_level": 0, 
    "human_hash": "div_X388_Y232_W1234_H287", 
    "index": -1, 
    "internal": {
        "elem_dict": {
            "attributes": {
                "class": "request-tests-editor text-editor-wrapper", 
                "style": "width: calc(100% - 250px);"
            }, 
            "background-color": "rgba(0, 0, 0, 0)", 
            "class": "div", 
            "color": "rgb(0, 0, 0)", 
            "cssClass": "request-tests-editor text-editor-wrapper", 
            "domLevel": 35, 
            "flags": {
                "checkable": false, 
                "clickable": false, 
                "enabled": false, 
                "focusable": false, 
                "focused": false, 
                "scrollable": false
            }, 
            "font-family": "Inter, OpenSans, Helvetica, Arial, sans-serif", 
            "font-weight": "400", 
            "fontSize": 12, 
            "height": 287, 
            "identifier": "", 
            "is-focused": false, 
            "is-hidden": false, 
            "name": "", 
            "tagName": "div", 
            "text": "1", 
            "type": "", 
            "value": "", 
            "width": 1234, 
            "x": 388, 
            "xPercent": 20.208333333333332, 
            "y": 232, 
            "yPercent": 26.185101580135438
        }, 
        "location": {
            "x": 388, 
            "y": 232
        }, 
        "size": {
            "height": 287, 
            "width": 1234
        }, 
        "tag_name": "div", 
        "text": "1"
    }, 
    "is_transformed": true, 
    "package": "", 
    "password": false, 
    "resource-id": "", 
    "scrollable": false, 
    "tag_name": "div", 
    "text": "1", 
    "transformed": true, 
    "width": 1234, 
    "x": 388, 
    "y": 232
}