{
    "behavior": "", 
    "checkable": false, 
    "class": "div", 
    "clickable": true, 
    "content-desc": "", 
    "enabled": false, 
    "focusable": true, 
    "focused": false, 
    "hash": "y5viyJ2w1ejpPVWlqxKS6Q==\n", 
    "height": 20, 
    "hier_level": 0, 
    "human_hash": "div_X1632_Y260_W158_H20", 
    "index": -1, 
    "internal": {
        "elem_dict": {
            "attributes": {
                "class": "btn btn-text snippet-header__help__link", 
                "tabindex": "0"
            }, 
            "background-color": "rgba(0, 0, 0, 0)", 
            "class": "div", 
            "color": "rgb(2, 101, 210)", 
            "cssClass": "btn btn-text snippet-header__help__link", 
            "domLevel": 40, 
            "flags": {
                "checkable": false, 
                "clickable": true, 
                "enabled": false, 
                "focusable": true, 
                "focused": false, 
                "scrollable": false
            }, 
            "font-family": "Inter, OpenSans, Helvetica, Arial, sans-serif", 
            "font-weight": "600", 
            "fontSize": 10, 
            "height": 20, 
            "identifier": "", 
            "is-focused": false, 
            "is-hidden": false, 
            "name": "", 
            "tagName": "div", 
            "text": "Learn more about tests scripts", 
            "type": "", 
            "value": "", 
            "width": 158, 
            "x": 1632, 
            "xPercent": 85, 
            "y": 260, 
            "yPercent": 29.345372460496616
        }, 
        "location": {
            "x": 1632, 
            "y": 260
        }, 
        "size": {
            "height": 20, 
            "width": 158
        }, 
        "tag_name": "div", 
        "text": "Learn more about tests scripts"
    }, 
    "is_transformed": true, 
    "package": "", 
    "password": false, 
    "resource-id": "", 
    "scrollable": false, 
    "tag_name": "div", 
    "text": "Learn more about tests scripts", 
    "transformed": true, 
    "width": 158, 
    "x": 1632, 
    "y": 260
}