{
    "behavior": "", 
    "checkable": false, 
    "class": "div", 
    "clickable": false, 
    "content-desc": "", 
    "enabled": false, 
    "focusable": false, 
    "focused": false, 
    "hash": "N8XCsr2aS9wDRzgPPnaOdQ==\n", 
    "height": 39, 
    "hier_level": 0, 
    "human_hash": "div_X676_Y48_W149_H39", 
    "index": -1, 
    "internal": {
        "elem_dict": {
            "attributes": {
                "class": "requester-tab", 
                "data-tab-id": "587b3b46-d5ad-40a5-a7fb-234dde3a93f0", 
                "draggable": "true"
            }, 
            "background-color": "rgb(255, 255, 255)", 
            "class": "div", 
            "color": "rgb(107, 107, 107)", 
            "cssClass": "requester-tab", 
            "domLevel": 18, 
            "flags": {
                "checkable": false, 
                "clickable": false, 
                "enabled": false, 
                "focusable": false, 
                "focused": false, 
                "scrollable": false
            }, 
            "font-family": "Inter, OpenSans, Helvetica, Arial, sans-serif", 
            "font-weight": "400", 
            "fontSize": 11, 
            "height": 39, 
            "identifier": "", 
            "is-focused": false, 
            "is-hidden": false, 
            "name": "", 
            "tagName": "div", 
            "text": "GETLabeler Objects", 
            "type": "", 
            "value": "", 
            "width": 149, 
            "x": 676, 
            "xPercent": 35.22135416666667, 
            "y": 48, 
            "yPercent": 5.417607223476298
        }, 
        "location": {
            "x": 676, 
            "y": 48
        }, 
        "size": {
            "height": 39, 
            "width": 149
        }, 
        "tag_name": "div", 
        "text": "GETLabeler Objects"
    }, 
    "is_transformed": true, 
    "package": "", 
    "password": false, 
    "resource-id": "", 
    "scrollable": false, 
    "tag_name": "div", 
    "text": "GETLabeler Objects", 
    "transformed": true, 
    "width": 149, 
    "x": 676, 
    "y": 48
}